gradio_neoviewer/__init__.py
gradio_neoviewer/neoviewer.py
gradio_neoviewer/neoviewer.pyi
gradio_neoviewer/templates/component/Index-DTyJKQrk.js
gradio_neoviewer/templates/component/index.js
gradio_neoviewer/templates/component/pdf-CNeaTg7E.js
gradio_neoviewer/templates/component/style.css
gradio_neoviewer/templates/example/index.js
gradio_neoviewer/templates/example/style.css
gradio_neoviewer-0.0.17.dist-info/METADATA
gradio_neoviewer-0.0.17.dist-info/WHEEL
gradio_neoviewer-0.0.17.dist-info/RECORD
